{
  "steps.json": {
    "lastUpdated": "2025-03-30T01:58:40.494Z",
    "hash": "cc3706d0ce5449b29cb7aa4132835aff"
  },
  "a-new-message-of-hope.json": {
    "lastUpdated": "2025-03-29T04:17:10.695Z",
    "hash": "364e6849830179e59a979faede3c945a"
  },
  "achievement.json": {
    "lastUpdated": "2025-03-29T04:17:10.696Z",
    "hash": "8071e0bf03038603c3d2049ac608e833"
  },
  "achieving-peace.json": {
    "lastUpdated": "2025-03-29T04:17:10.698Z",
    "hash": "1e63b993ffd393d7e14be90c6463cfa7"
  },
  "adapting-to-a-changing-world.json": {
    "lastUpdated": "2025-03-29T04:17:10.699Z",
    "hash": "9a068afa93edf08c078caa4e8bf90cca"
  },
  "ambition-personal-true-way.json": {
    "lastUpdated": "2025-03-29T04:17:10.700Z",
    "hash": "8002502e32f1687faf0a66fb309d17c3"
  },
  "approaching-the-new-message.json": {
    "lastUpdated": "2025-03-29T04:17:10.702Z",
    "hash": "0c3155df3ef718c88dcf3e184255e918"
  },
  "avoiding-disaster.json": {
    "lastUpdated": "2025-03-29T04:17:10.703Z",
    "hash": "70dd53bea462142935f480483a155ed2"
  },
  "battleground-conflict-war.json": {
    "lastUpdated": "2025-03-29T04:17:10.704Z",
    "hash": "8b324cf7512705043e0f7269ec18a0c7"
  },
  "becoming-wise-wisdom.json": {
    "lastUpdated": "2025-03-29T04:17:10.706Z",
    "hash": "995d78ea73f8d99ec20aa588855bf20a"
  },
  "beginning-preparation-respond-calling.json": {
    "lastUpdated": "2025-03-29T04:17:10.707Z",
    "hash": "1010445b775ae217a38172cd6e868481"
  },
  "being-a-person-of-the-new-message.json": {
    "lastUpdated": "2025-03-29T04:17:10.708Z",
    "hash": "4a3575de6fa1eeb61d36bd02f2e4ac03"
  },
  "being-a-student-of-the-new-message.json": {
    "lastUpdated": "2025-03-29T04:17:10.709Z",
    "hash": "f01a6902cec12307c70547935c75ae94"
  },
  "being-alone.json": {
    "lastUpdated": "2025-03-29T04:17:10.710Z",
    "hash": "dfada67c5390aed8880ff7a11ddab668"
  },
  "being-centered-crashing-world.json": {
    "lastUpdated": "2025-03-29T04:17:10.711Z",
    "hash": "134db3cc38c6c360da247bb34aa8e221"
  },
  "being-present-still-mind.json": {
    "lastUpdated": "2025-03-29T04:17:10.713Z",
    "hash": "4ea36c2b88561ad15b5d507063b88fae"
  },
  "beneath-surface.json": {
    "lastUpdated": "2025-03-29T04:17:10.714Z",
    "hash": "1de1830855ef74249e7ac8ac7905ae87"
  },
  "beyond-human-religion.json": {
    "lastUpdated": "2025-03-29T04:17:10.715Z",
    "hash": "f72e90cde07967e59f83f61de739411e"
  },
  "bridge-two-minds.json": {
    "lastUpdated": "2025-03-29T04:17:10.716Z",
    "hash": "e69b5f97e0ec8d0135fe05abba5c1b8a"
  },
  "bringing-balance-and-security-to-the-world.json": {
    "lastUpdated": "2025-03-29T04:17:10.717Z",
    "hash": "9529b357eda4d375aabe7e8d8f31f3dc"
  },
  "bringing-the-new-message-to-the-world.json": {
    "lastUpdated": "2025-03-29T04:17:10.718Z",
    "hash": "ac009d597037a2b1f7bbe53af8dce79c"
  },
  "buddha-and-the-new-message-from-god.json": {
    "lastUpdated": "2025-03-29T04:17:10.719Z",
    "hash": "2f1cb59b958e9ac773fea19cad8f7fed"
  },
  "building-spiritual-community.json": {
    "lastUpdated": "2025-03-29T04:17:10.721Z",
    "hash": "9254cd8f6b920ad8f9f00e4343046577"
  },
  "building-strength-resilience.json": {
    "lastUpdated": "2025-03-29T04:17:10.722Z",
    "hash": "a246e53c5d7ec7b3b1a0473620c0b15f"
  },
  "building-the-bridge-to-a-new-life.json": {
    "lastUpdated": "2025-03-29T04:17:10.723Z",
    "hash": "86adae06818241c8889d9b911e71d811"
  },
  "building-your-ark.json": {
    "lastUpdated": "2025-03-29T04:17:10.724Z",
    "hash": "f23a8506a99112ee9039a84f916b19c9"
  },
  "burden-of-the-messenger.json": {
    "lastUpdated": "2025-03-29T04:17:10.725Z",
    "hash": "1bf30f77da8ea914c3c5fba0d58506f4"
  },
  "compassion-means.json": {
    "lastUpdated": "2025-03-29T04:17:10.726Z",
    "hash": "11c149492078dd9fa21dd0603cf8788b"
  },
  "completing-relationships-when-over.json": {
    "lastUpdated": "2025-03-29T04:17:10.728Z",
    "hash": "47035ff406ee31942e2a6c1c0e92e581"
  },
  "comprehending-god.json": {
    "lastUpdated": "2025-03-29T04:17:10.729Z",
    "hash": "2d5e121c36d718b79122a5c12dfba5af"
  },
  "concentrated-mind.json": {
    "lastUpdated": "2025-03-29T04:17:10.731Z",
    "hash": "0e352f83e84f627d6927a698ccf671d4"
  },
  "courage-and-the-will-to-prepare.json": {
    "lastUpdated": "2025-03-29T04:17:10.732Z",
    "hash": "1174829229a05d0b5c1ae00247e03676"
  },
  "courage-face-yourself.json": {
    "lastUpdated": "2025-03-29T04:17:10.732Z",
    "hash": "b06d000e95ea8795e0cd2f02d5da5c63"
  },
  "dealing-with-resistance-and-hostility.json": {
    "lastUpdated": "2025-03-29T04:17:10.734Z",
    "hash": "633728bf360d968ffd852bf9e8a27f63"
  },
  "deep-union-god.json": {
    "lastUpdated": "2025-03-29T04:17:10.735Z",
    "hash": "3982efe56c211b435974f82e56fb1d2c"
  },
  "deepening-your-spiritual-practice.json": {
    "lastUpdated": "2025-03-29T04:17:10.737Z",
    "hash": "94bd6c5d698f2b04d47b5646329be8a8"
  },
  "deeper-connection-relationships.json": {
    "lastUpdated": "2025-03-29T04:17:10.737Z",
    "hash": "8b4d96758d8935fe02f4cbd1d94454a6"
  },
  "desire-freedom.json": {
    "lastUpdated": "2025-03-29T04:17:10.739Z",
    "hash": "079b7dd4533165532101202214f58ba8"
  },
  "destiny.json": {
    "lastUpdated": "2025-03-29T04:17:10.740Z",
    "hash": "e7e52c693aa0de436154c4e4d1bb286d"
  },
  "develop-greater-concentration.json": {
    "lastUpdated": "2025-03-29T04:17:10.741Z",
    "hash": "cc6e1aea7cc06a2382f8a440f50dd713"
  },
  "developing-strength-wisdom.json": {
    "lastUpdated": "2025-03-29T04:17:10.742Z",
    "hash": "3f360074f08a552f443b84975d103e17"
  },
  "disappointment.json": {
    "lastUpdated": "2025-03-29T04:17:10.743Z",
    "hash": "8740b6c55505adc95256bfa37784a868"
  },
  "discernment-how-to-see.json": {
    "lastUpdated": "2025-03-29T04:17:10.744Z",
    "hash": "c5600c988e6226833ee7a2323da47f40"
  },
  "discernment-in-relationships.json": {
    "lastUpdated": "2025-03-29T04:17:10.746Z",
    "hash": "eb33bfa3ca1ce553a75bfbe660b18e66"
  },
  "end-war-human-unity.json": {
    "lastUpdated": "2025-03-29T04:17:10.747Z",
    "hash": "df7e7cc47fed402863205c88b8e1d7e9"
  },
  "enduring-happiness.json": {
    "lastUpdated": "2025-03-29T04:17:10.748Z",
    "hash": "b4daf13505096c5ff0702f74233af895"
  },
  "enduring-love.json": {
    "lastUpdated": "2025-03-29T04:17:10.749Z",
    "hash": "292783824a96dc06e1d2a92913740919"
  },
  "enemies-human-family.json": {
    "lastUpdated": "2025-03-29T04:17:10.751Z",
    "hash": "0914f0aff9eea3b591bf51047154a976"
  },
  "escaping-fear-confusion-and-hopelessness.json": {
    "lastUpdated": "2025-03-29T04:17:10.752Z",
    "hash": "e1b8555fdee1c2c3f09db663471348b8"
  },
  "escaping-fear.json": {
    "lastUpdated": "2025-03-29T04:17:10.753Z",
    "hash": "5188384088c1618566a50d0619b5f8a6"
  },
  "escaping-the-past.json": {
    "lastUpdated": "2025-03-29T04:17:10.754Z",
    "hash": "525580237666a41d07a3af5689de7ac5"
  },
  "essential-relationships-others.json": {
    "lastUpdated": "2025-03-29T04:17:10.755Z",
    "hash": "2a5a263a0fee1e90ff8a48208e95fb6d"
  },
  "essential-truths-other-forms-life.json": {
    "lastUpdated": "2025-03-29T04:17:10.756Z",
    "hash": "002fff8f6b51a90e3f33d393a76baf1e"
  },
  "establishing-meaningful-relationships.json": {
    "lastUpdated": "2025-03-29T04:17:10.758Z",
    "hash": "44645bb0328df93fd6d0394653823375"
  },
  "experience-relationship-conclusion.json": {
    "lastUpdated": "2025-03-29T04:17:10.759Z",
    "hash": "912a84ca2802fb73be749c92049d518f"
  },
  "experiencing-god.json": {
    "lastUpdated": "2025-03-29T04:17:10.760Z",
    "hash": "ca159e33bbe4f941eb939cdcef649f2f"
  },
  "experiencing-presence-god.json": {
    "lastUpdated": "2025-03-29T04:17:10.761Z",
    "hash": "c2cc7daf053835f840699c88a2966873"
  },
  "experiencing-your-higher-purpose.json": {
    "lastUpdated": "2025-03-29T04:17:10.762Z",
    "hash": "11da018ee0f4304a2e3932a946166236"
  },
  "extraterrestrial-encounters.json": {
    "lastUpdated": "2025-03-29T04:17:10.763Z",
    "hash": "0687849bcc35dfafaf405be5efff2feb"
  },
  "extraterrestrial-technology.json": {
    "lastUpdated": "2025-03-29T04:17:10.764Z",
    "hash": "0cc8a2253cb275e14d21181c65efa4bf"
  },
  "facing-a-world-in-decline.json": {
    "lastUpdated": "2025-03-29T04:17:10.765Z",
    "hash": "3645ce67f9bac5bac252c7e4b7babc09"
  },
  "facing-great-change-in-the-world.json": {
    "lastUpdated": "2025-03-29T04:17:10.766Z",
    "hash": "157bd41c4d4c4003d17ccb4dcc52459f"
  },
  "facing-light-revelation.json": {
    "lastUpdated": "2025-03-29T04:17:10.767Z",
    "hash": "d8435561d79dcff397de2d74f3735916"
  },
  "facing-pandemic-today.json": {
    "lastUpdated": "2025-03-29T04:17:10.768Z",
    "hash": "05f5e44b34af26663111d68f733de700"
  },
  "faith-fear-idea-self.json": {
    "lastUpdated": "2025-03-29T04:17:10.769Z",
    "hash": "aa5e5edd5cf195a65726df9a80b93c55"
  },
  "faith-work-and-higher-purpose.json": {
    "lastUpdated": "2025-03-29T04:17:10.770Z",
    "hash": "72c50f1b1352cfefef07ed7eed1d3447"
  },
  "false-expectations-of-god.json": {
    "lastUpdated": "2025-03-29T04:17:10.771Z",
    "hash": "95cd5cee0990df4c9389316d105c7928"
  },
  "financial-storms.json": {
    "lastUpdated": "2025-03-29T04:17:10.772Z",
    "hash": "cb6de08e10ea039b8877adfb2d9621a4"
  },
  "finding-certainty-and-strength.json": {
    "lastUpdated": "2025-03-29T04:17:10.773Z",
    "hash": "2eb5fc9dff03200713778d567df28f7c"
  },
  "finding-knowledge-spiritual-nature.json": {
    "lastUpdated": "2025-03-29T04:17:10.775Z",
    "hash": "4cca78b5e38d3f2f386970fd0f445fa4"
  },
  "first-commitment-relationship-god.json": {
    "lastUpdated": "2025-03-29T04:17:10.776Z",
    "hash": "addc3ccda148ca42aaf413b980ae57c9"
  },
  "following-presence-god.json": {
    "lastUpdated": "2025-03-29T04:17:10.777Z",
    "hash": "b1ba4c18e4febb941780a098bc0fd82a"
  },
  "food-water-and-energy.json": {
    "lastUpdated": "2025-03-29T04:17:10.779Z",
    "hash": "c77f4cf6e37b826269f47924cd45447f"
  },
  "forces-good.json": {
    "lastUpdated": "2025-03-29T04:17:10.780Z",
    "hash": "2a944543e7488ceafacc5127b1cc0ce6"
  },
  "foreign-powers-beyond-world.json": {
    "lastUpdated": "2025-03-29T04:17:10.781Z",
    "hash": "ec5da3b47c9b0dbf335fcced30fbb4ec"
  },
  "forgiveness.json": {
    "lastUpdated": "2025-03-29T04:17:10.782Z",
    "hash": "a6ab600e2f5307c49c5ecd19cc251774"
  },
  "foundation-greater-life-strength.json": {
    "lastUpdated": "2025-03-29T04:17:10.783Z",
    "hash": "38b7eef35bb0cb1b500264b025b7d323"
  },
  "free-energy-alien-technologies.json": {
    "lastUpdated": "2025-03-29T04:17:10.784Z",
    "hash": "ef020b468bf5c1268d0e692e3dad2c07"
  },
  "freedom-journey.json": {
    "lastUpdated": "2025-03-29T04:17:10.785Z",
    "hash": "1799903cf35053a19287524ee0fd7fb0"
  },
  "freedom.json": {
    "lastUpdated": "2025-03-29T04:17:10.786Z",
    "hash": "512a484f600e7b5ad5dc0f6dc66737cd"
  },
  "fulfillment.json": {
    "lastUpdated": "2025-03-29T04:17:10.787Z",
    "hash": "ad895624777da880b459a58d5ed37784"
  },
  "future-humanity.json": {
    "lastUpdated": "2025-03-29T04:17:10.788Z",
    "hash": "fe4d45b9b8c7db439ab555be54607be4"
  },
  "gaining-strength-inner-authority.json": {
    "lastUpdated": "2025-03-29T04:17:10.789Z",
    "hash": "cc5689215a241531658b36941df5396b"
  },
  "genetic-manipulation-humans.json": {
    "lastUpdated": "2025-03-29T04:17:10.791Z",
    "hash": "9f4f0531ef6fda95ca5b0d142bc180ac"
  },
  "giving-i.json": {
    "lastUpdated": "2025-03-29T04:17:10.793Z",
    "hash": "1b9ecb1176fffacb5e4a05c8e0ce6bf6"
  },
  "giving-ii.json": {
    "lastUpdated": "2025-03-29T04:17:10.794Z",
    "hash": "6aed6096cd11a375041d42747d8bb8e2"
  },
  "global-security-facing-reality.json": {
    "lastUpdated": "2025-03-29T04:17:10.795Z",
    "hash": "a68f7b182b576a3aaed745f3888c4661"
  },
  "god-has-spoken.json": {
    "lastUpdated": "2025-03-29T04:17:10.796Z",
    "hash": "7118ca681702db968f06771c0f1d6e71"
  },
  "god-is-moving-humanity-in-a-new-direction.json": {
    "lastUpdated": "2025-03-29T04:17:10.796Z",
    "hash": "f72e95e01d36fdfb188e342aa17e74b9"
  },
  "god-is-moving-humanity.json": {
    "lastUpdated": "2025-03-29T04:17:10.798Z",
    "hash": "1f19187c67e34d50fcbc8c2860dd01bb"
  },
  "god-knowledge-and-the-angelic-presence.json": {
    "lastUpdated": "2025-03-29T04:17:10.799Z",
    "hash": "019198b706ddb10c46db7f2ae06b63b8"
  },
  "gods-ancient-covenant-with-humanity.json": {
    "lastUpdated": "2025-03-29T04:17:10.800Z",
    "hash": "f1eae7fb19661d94dbdfa3db214854a4"
  },
  "gods-new-message-for-political-leaders.json": {
    "lastUpdated": "2025-03-29T04:17:10.802Z",
    "hash": "b9ed58607b2f0e1f351be7c5142ad9c4"
  },
  "gods-new-message-for-the-islamic-world.json": {
    "lastUpdated": "2025-03-29T04:17:10.803Z",
    "hash": "b8b32cf4579d1d6a05106ea9f854bfe9"
  },
  "gods-new-message-for-the-world.json": {
    "lastUpdated": "2025-03-29T04:17:10.804Z",
    "hash": "a9e459e45b5fddb62da7f88df8ca12b7"
  },
  "gods-new-message-for-the-worlds-religions.json": {
    "lastUpdated": "2025-03-29T04:17:10.805Z",
    "hash": "788a347fbd27b128045c9aed81bedb54"
  },
  "gods-plan-for-the-world.json": {
    "lastUpdated": "2025-03-29T04:17:10.806Z",
    "hash": "5b2d071b555d082e909485439d32fbaf"
  },
  "gods-plan-save-everyone.json": {
    "lastUpdated": "2025-03-29T04:17:10.808Z",
    "hash": "b5a41c279bde96302f7b3a2a8f52b00f"
  },
  "gods-power-in-you.json": {
    "lastUpdated": "2025-03-29T04:17:10.810Z",
    "hash": "c89b33668e1545b4f12288389255d49a"
  },
  "going-beneath-the-surface-of-the-mind.json": {
    "lastUpdated": "2025-03-29T04:17:10.813Z",
    "hash": "af2b58f5959c194221c9b5e15c8406b2"
  },
  "grace.json": {
    "lastUpdated": "2025-03-29T04:17:10.815Z",
    "hash": "d4a1dd1e001c4bbfa6874ce7344798a3"
  },
  "great-attraction.json": {
    "lastUpdated": "2025-03-29T04:17:10.818Z",
    "hash": "b644b6ad9eb89229cdae6bf1ca03577d"
  },
  "great-challenge-become-aware.json": {
    "lastUpdated": "2025-03-29T04:17:10.820Z",
    "hash": "997b6f79ca21d4302562660c44dd7424"
  },
  "great-relationships-destiny.json": {
    "lastUpdated": "2025-03-29T04:17:10.824Z",
    "hash": "57ae77b3eb05fba373adcaca390cf525"
  },
  "great-transition-one-world-community.json": {
    "lastUpdated": "2025-03-29T04:17:10.827Z",
    "hash": "74e2225c86d5d87edae5673ddf0d0df5"
  },
  "great-truth-god.json": {
    "lastUpdated": "2025-03-29T04:17:10.830Z",
    "hash": "6125264d38b3575d68fc939e17633274"
  },
  "greater-community-reality.json": {
    "lastUpdated": "2025-03-29T04:17:10.832Z",
    "hash": "10cfa2e62b382fccfe05b819682a0ded"
  },
  "greater-honesty-mind.json": {
    "lastUpdated": "2025-03-29T04:17:10.835Z",
    "hash": "20de29bb78455eaa94373e6c1a97b578"
  },
  "greater-intelligence.json": {
    "lastUpdated": "2025-03-29T04:17:10.836Z",
    "hash": "cd5dd6696083b9811c0e41d0ee13c1b3"
  },
  "greater-pleasure.json": {
    "lastUpdated": "2025-03-29T04:17:10.837Z",
    "hash": "bfbec269d101ce2da76ea8ecd13bb5d6"
  },
  "greater-power.json": {
    "lastUpdated": "2025-03-29T04:17:10.839Z",
    "hash": "18ba26d202a657d789e107ccfc68777a"
  },
  "greater-purpose-life.json": {
    "lastUpdated": "2025-03-29T04:17:10.843Z",
    "hash": "33dd66c2adb744d535b33c547b419211"
  },
  "greater-work-pillar.json": {
    "lastUpdated": "2025-03-29T04:17:10.845Z",
    "hash": "5d21d0923e0a2279e5db733dd754b04a"
  },
  "group-mind.json": {
    "lastUpdated": "2025-03-29T04:17:10.847Z",
    "hash": "957df48d35c6376ccc32ca1ed0706bb0"
  },
  "guidelines-for-discovering-your-higher-purpose.json": {
    "lastUpdated": "2025-03-29T04:17:10.849Z",
    "hash": "45b5560616e6c97f672a57689ed5ca0f"
  },
  "guidelines-for-preparing-for-the-greater-community.json": {
    "lastUpdated": "2025-03-29T04:17:10.850Z",
    "hash": "400ed9d3d976f860cbe30e141525d987"
  },
  "happiness-in-the-world.json": {
    "lastUpdated": "2025-03-29T04:17:10.852Z",
    "hash": "7a33bf1b1a7b2dd36a2f807a39fe6a95"
  },
  "harmful-influences.json": {
    "lastUpdated": "2025-03-29T04:17:10.853Z",
    "hash": "5850d652c6b26db9fb37f015afd9ae72"
  },
  "healing-relationships-past.json": {
    "lastUpdated": "2025-03-29T04:17:10.857Z",
    "hash": "0835a75d4e001dce3e6b660459f74042"
  },
  "healing.json": {
    "lastUpdated": "2025-03-29T04:17:10.859Z",
    "hash": "5de835d20e3200b3658d45d97e8d5b90"
  },
  "health.json": {
    "lastUpdated": "2025-03-29T04:17:10.860Z",
    "hash": "e5047837db3f90d532a21b3a6a164aca"
  },
  "heaven-and-hell.json": {
    "lastUpdated": "2025-03-29T04:17:10.861Z",
    "hash": "cf5518ade413a1e5261c45220dcc037b"
  },
  "here-unique-contribution.json": {
    "lastUpdated": "2025-03-29T04:17:10.862Z",
    "hash": "1737cd2285c58853202932a00b2426c7"
  },
  "higher-vantage-point.json": {
    "lastUpdated": "2025-03-29T04:17:10.863Z",
    "hash": "1f29d6dd9b47d68130208b8062eee825"
  },
  "honesty-present-mind.json": {
    "lastUpdated": "2025-03-29T04:17:10.865Z",
    "hash": "a73200af3301947566fdc8ab2eb8e9be"
  },
  "how-do-you-prepare.json": {
    "lastUpdated": "2025-03-29T04:17:10.866Z",
    "hash": "c4ca060272be53262dc1e91161faeb74"
  },
  "how-does-revelation-occur-in-human-life.json": {
    "lastUpdated": "2025-03-29T04:17:10.868Z",
    "hash": "0f0d56cd9525918d67d360c6bb05106a"
  },
  "how-god-speaks-to-the-world.json": {
    "lastUpdated": "2025-03-29T04:17:10.869Z",
    "hash": "cff8f97aed4a0dcd7f93122db4ba04f3"
  },
  "how-is-knowledge-translated-in-the-greater-community.json": {
    "lastUpdated": "2025-03-29T04:17:10.871Z",
    "hash": "97b59a09c8cc4794830ab56986eb6a94"
  },
  "how-is-wisdom-achieved-in-life.json": {
    "lastUpdated": "2025-03-29T04:17:10.873Z",
    "hash": "13275db5e4e4c73487200820a2ba0c27"
  },
  "how-to-live.json": {
    "lastUpdated": "2025-03-29T04:17:10.876Z",
    "hash": "fdf012ac6fcac3159a8f23d29bbe125b"
  },
  "how-to-regard-the-messenger.json": {
    "lastUpdated": "2025-03-29T04:17:10.877Z",
    "hash": "e3458ff9f77ee05154d1b16a8fcf7d1f"
  },
  "human-isolation-over.json": {
    "lastUpdated": "2025-03-29T04:17:10.878Z",
    "hash": "bfdae7e63e12ec510bacf231b2285b6e"
  },
  "human-unity.json": {
    "lastUpdated": "2025-03-29T04:17:10.879Z",
    "hash": "6821387c965b410c53db9e6346b887a3"
  },
  "humanitys-destiny-in-the-greater-community.json": {
    "lastUpdated": "2025-03-29T04:17:10.880Z",
    "hash": "cfb5c641ccd67b99f5eb54594ad85f25"
  },
  "humanitys-emergence-into-the-greater-community.json": {
    "lastUpdated": "2025-03-29T04:17:10.882Z",
    "hash": "c69d96d59a4c040547b52c7b0ea8dd60"
  },
  "ideas-beliefs-god.json": {
    "lastUpdated": "2025-03-29T04:17:10.883Z",
    "hash": "d0e2dd7b991a742c96abbb44f9cd5a3e"
  },
  "illness-and-healing.json": {
    "lastUpdated": "2025-03-29T04:17:10.884Z",
    "hash": "972a1a49584cf838d2a04a583fe6742b"
  },
  "importance-greater-community.json": {
    "lastUpdated": "2025-03-29T04:17:10.885Z",
    "hash": "5900713a8e7e54b9ecb552545af9c35c"
  },
  "individual-freedom.json": {
    "lastUpdated": "2025-03-29T04:17:10.886Z",
    "hash": "2a718c742b80824425e403ad28b6f4ad"
  },
  "inner-listening.json": {
    "lastUpdated": "2025-03-29T04:17:10.887Z",
    "hash": "9c85f39bae31430452d3ab1c59605bff"
  },
  "intelligent-life-in-the-universe.json": {
    "lastUpdated": "2025-03-29T04:17:10.888Z",
    "hash": "b45b03764d57e8f018af92e7b83da107"
  },
  "intelligent-life-universe.json": {
    "lastUpdated": "2025-03-29T04:17:10.889Z",
    "hash": "aae883d84e9449ab57cd57b312ba84ca"
  },
  "interdependence.json": {
    "lastUpdated": "2025-03-29T04:17:10.890Z",
    "hash": "f325525d3ab8eb9dd95334fa4a3a31b7"
  },
  "interstellar-trade.json": {
    "lastUpdated": "2025-03-29T04:17:10.891Z",
    "hash": "a858bc80900e79aa4e0d099977c2b090"
  },
  "jesus-and-the-new-message.json": {
    "lastUpdated": "2025-03-29T04:17:10.893Z",
    "hash": "00685fbc1c5c3de169909ed3720d9a45"
  },
  "joy-gratitude.json": {
    "lastUpdated": "2025-03-29T04:17:10.894Z",
    "hash": "b239847bc23faa633bed2ca1f7c21788"
  },
  "kindness-is-acceptance-understanding.json": {
    "lastUpdated": "2025-03-29T04:17:10.895Z",
    "hash": "846cdf1532d8317b09ef5b040bf82627"
  },
  "know-what-to-do.json": {
    "lastUpdated": "2025-03-29T04:17:10.896Z",
    "hash": "7559be714a0c71bd2a20259bae82c5dd"
  },
  "lamp.json": {
    "lastUpdated": "2025-03-29T04:17:10.897Z",
    "hash": "1653c107400c859a36e9fede16339693"
  },
  "learn-others-want-learn.json": {
    "lastUpdated": "2025-03-29T04:17:10.898Z",
    "hash": "7564fd67e8223b1627b8253ba6f220ab"
  },
  "life-beyond-solar-system.json": {
    "lastUpdated": "2025-03-29T04:17:10.900Z",
    "hash": "a4d04e7bc3f5119d8c3ef8b45238e757"
  },
  "life-beyond.json": {
    "lastUpdated": "2025-03-29T04:17:10.901Z",
    "hash": "cbbf2b07d2c2d932b5dac1d175adf755"
  },
  "lineage-messenger.json": {
    "lastUpdated": "2025-03-29T04:17:10.902Z",
    "hash": "ef7f77ec808f4205c9edbde6e89fa628"
  },
  "living-at-a-time-of-revelation.json": {
    "lastUpdated": "2025-03-29T04:17:10.904Z",
    "hash": "07af55db7731bb792a91a52dfeb63f45"
  },
  "living-in-a-time-of-uncertainty-and-instability.json": {
    "lastUpdated": "2025-03-29T04:17:10.906Z",
    "hash": "8f2b8332832a06cbd2bde1db4e9d6028"
  },
  "living-in-an-emerging-world.json": {
    "lastUpdated": "2025-03-29T04:17:10.907Z",
    "hash": "7cc5d8a9f1ba947c20a42f34dadf734a"
  },
  "living-separation-alone-afraid.json": {
    "lastUpdated": "2025-03-29T04:17:10.908Z",
    "hash": "e4b93dabf37e89d9b5b3825f8d04b2cf"
  },
  "love-and-relationships.json": {
    "lastUpdated": "2025-03-29T04:17:10.909Z",
    "hash": "8a3a99a4eb61817ba8d044552d608969"
  },
  "love.json": {
    "lastUpdated": "2025-03-29T04:17:10.911Z",
    "hash": "6f56556fb334a72692dd9303101d5d6a"
  },
  "maintaining-relationships-spiritual.json": {
    "lastUpdated": "2025-03-29T04:17:10.912Z",
    "hash": "0a093f26774d39950d8c818eedfb6b1c"
  },
  "marriage-and-higher-purpose.json": {
    "lastUpdated": "2025-03-29T04:17:10.913Z",
    "hash": "8e2c442fe0f4702444072799a9375786"
  },
  "marriage-consummate-relationship-devotion.json": {
    "lastUpdated": "2025-03-29T04:17:10.914Z",
    "hash": "9790253d55b10836a3cabb37914ca744"
  },
  "marriage.json": {
    "lastUpdated": "2025-03-29T04:17:10.915Z",
    "hash": "ad986fa4cfa08c4f1f7eaba428279e65"
  },
  "mastery.json": {
    "lastUpdated": "2025-03-29T04:17:10.916Z",
    "hash": "c537819f3f4f872fcf33f3ac13d9453d"
  },
  "meaning-spiritual-development.json": {
    "lastUpdated": "2025-03-29T04:17:10.917Z",
    "hash": "38165b06f707cd6f0ecf4e1fe7a5fac1"
  },
  "message-young-people.json": {
    "lastUpdated": "2025-03-29T04:17:10.918Z",
    "hash": "3ab6bf085920b247758e7cbf26692d94"
  },
  "mission-of-the-messenger.json": {
    "lastUpdated": "2025-03-29T04:17:10.919Z",
    "hash": "d40d4876fa27b466f6c7406cf8cddeb5"
  },
  "money-resource-relationship.json": {
    "lastUpdated": "2025-03-29T04:17:10.920Z",
    "hash": "719f1e4c35c5ec3f37aed6f6a68889b2"
  },
  "muhammad-and-the-nm.json": {
    "lastUpdated": "2025-03-29T04:17:10.921Z",
    "hash": "db79ac811d00d40f2a7e4b2daaa80414"
  },
  "my-role-greater-purpose.json": {
    "lastUpdated": "2025-03-29T04:17:10.923Z",
    "hash": "4bade38936800ece6752b23800129f8c"
  },
  "natural-environment.json": {
    "lastUpdated": "2025-03-29T04:17:10.924Z",
    "hash": "8ec459ea07cf0da6c25380cf4e050f89"
  },
  "nature-and-natural-disasters.json": {
    "lastUpdated": "2025-03-29T04:17:10.925Z",
    "hash": "a5cc204594d9650bddf2aedf4fe33885"
  },
  "navigating-difficult-times-ahead.json": {
    "lastUpdated": "2025-03-29T04:17:10.928Z",
    "hash": "7bb55fb1cf47f8583bdd78ef25a7426e"
  },
  "new-god-revelation.json": {
    "lastUpdated": "2025-03-29T04:17:10.931Z",
    "hash": "657b4aafe93c9431e3b184558feabf5b"
  },
  "new-world-prophecy.json": {
    "lastUpdated": "2025-03-29T04:17:10.933Z",
    "hash": "a6de29f6fe4a4eb934dc604efe225cd3"
  },
  "new-world.json": {
    "lastUpdated": "2025-03-29T04:17:10.936Z",
    "hash": "96c5113bc9b4d073de5a5d758d506514"
  },
  "not-worry-future.json": {
    "lastUpdated": "2025-03-29T04:17:10.940Z",
    "hash": "aa0cdf79851a9e92678525402e902b20"
  },
  "origin-messenger.json": {
    "lastUpdated": "2025-03-29T04:17:10.941Z",
    "hash": "da9bad9e9b101a989704e3e8cf9f6818"
  },
  "other-worlds-reality.json": {
    "lastUpdated": "2025-03-29T04:17:10.942Z",
    "hash": "c2c432587f2316916a9af27ba50203d3"
  },
  "perseverance-give-yourself.json": {
    "lastUpdated": "2025-03-29T04:17:10.943Z",
    "hash": "656a02a0f7172eac934b540daa739d75"
  },
  "personal-development.json": {
    "lastUpdated": "2025-03-29T04:17:10.944Z",
    "hash": "e9b768c7411d81d9c57cb69296ff2dd8"
  },
  "personal-freedom.json": {
    "lastUpdated": "2025-03-29T04:17:10.945Z",
    "hash": "94dfe14decd92b9fcdf82c3e769d6515"
  },
  "personal-revelation.json": {
    "lastUpdated": "2025-03-29T04:17:10.946Z",
    "hash": "d626864d672461e0bd6558d4d7bcd9ae"
  },
  "personal-side-develop-trust.json": {
    "lastUpdated": "2025-03-29T04:17:10.947Z",
    "hash": "9323981a6d861d3c847a7e20a389d62e"
  },
  "physical-universe.json": {
    "lastUpdated": "2025-03-29T04:17:10.949Z",
    "hash": "29daf56b465bb900774138150c195138"
  },
  "planetary-instability.json": {
    "lastUpdated": "2025-03-29T04:17:10.950Z",
    "hash": "45609018f767c022b36f6b61d188a2df"
  },
  "plight-humanity-waves-change.json": {
    "lastUpdated": "2025-03-29T04:17:10.951Z",
    "hash": "037e33aef6b155f4b82de1590bfba6e5"
  },
  "possessions.json": {
    "lastUpdated": "2025-03-29T04:17:10.952Z",
    "hash": "0422cd03af3e02dc9d0cd2c200140a7c"
  },
  "poverty.json": {
    "lastUpdated": "2025-03-29T04:17:10.953Z",
    "hash": "e40d0f403daf679e04335d72b27975a0"
  },
  "power-and-responsibility.json": {
    "lastUpdated": "2025-03-29T04:17:10.954Z",
    "hash": "68cc8c2a28d745b5a61a65e9a4e3e44f"
  },
  "power-knowledge.json": {
    "lastUpdated": "2025-03-29T04:17:10.955Z",
    "hash": "b42d8fb895ddf0539d73f3626c70dc1b"
  },
  "power-of-knowledge-other.json": {
    "lastUpdated": "2025-03-29T04:17:10.957Z",
    "hash": "eb4d641a75efdac984fd5abd0da31cff"
  },
  "power-persuasion.json": {
    "lastUpdated": "2025-03-29T04:17:10.958Z",
    "hash": "bdb640c2985b537a840f4071e0cf1742"
  },
  "preception-interpretation-reality.json": {
    "lastUpdated": "2025-03-29T04:17:10.959Z",
    "hash": "c78cc0feec2b8dc51b3e80078b7af2b7"
  },
  "preparing-for-the-future-2.json": {
    "lastUpdated": "2025-03-29T04:17:10.960Z",
    "hash": "7373a3ea2e9416b588992f27523bb5ae"
  },
  "preparing-for-the-future.json": {
    "lastUpdated": "2025-03-29T04:17:10.962Z",
    "hash": "fadddf9781b32bc9ea0bc50ea807bae4"
  },
  "preparing-for-the-greater-community.json": {
    "lastUpdated": "2025-03-29T04:17:10.963Z",
    "hash": "2a9aa5c166edb2062dce7199944f6326"
  },
  "preparing-your-family.json": {
    "lastUpdated": "2025-03-29T04:17:10.965Z",
    "hash": "da44f90975f5e5bc4f1cd86858922ab9"
  },
  "preventing-collapse-wars-of-desperation.json": {
    "lastUpdated": "2025-03-29T04:17:10.966Z",
    "hash": "9f24f70c76e806b734edebcccddce0a5"
  },
  "pride.json": {
    "lastUpdated": "2025-03-29T04:17:10.967Z",
    "hash": "8861feb69ddd251d71a4d226c7ef12ca"
  },
  "prison-escape-your-mind.json": {
    "lastUpdated": "2025-03-29T04:17:10.968Z",
    "hash": "2a7afe6a4c58a66e0c510b9690790cfd"
  },
  "problem-evil.json": {
    "lastUpdated": "2025-03-29T04:17:10.970Z",
    "hash": "09be11415874fbe950d1666c30ee1119"
  },
  "problem-sin-power-redemption.json": {
    "lastUpdated": "2025-03-29T04:17:10.971Z",
    "hash": "41b1cfaa4e0ea46710f9570be0d896ca"
  },
  "problem-suffering-greater-happiness.json": {
    "lastUpdated": "2025-03-29T04:17:10.973Z",
    "hash": "171438edde93b582b4b932bd5d2e3675"
  },
  "protecting-the-message-and-the-messenger.json": {
    "lastUpdated": "2025-03-29T04:17:10.975Z",
    "hash": "aed1cc5d2372796a384f3ed16749e856"
  },
  "protecting-the-world.json": {
    "lastUpdated": "2025-03-29T04:17:10.977Z",
    "hash": "3b8c35a558d053fdf70cd75924b12082"
  },
  "protecting-yourself-from-the-intervention.json": {
    "lastUpdated": "2025-03-29T04:17:10.978Z",
    "hash": "4e2e3ec4648e1a3da5b0930a450fb9ec"
  },
  "provoking-change.json": {
    "lastUpdated": "2025-03-29T04:17:10.980Z",
    "hash": "58c07c7eb28bcafc777e15125e354ec6"
  },
  "raising-children.json": {
    "lastUpdated": "2025-03-29T04:17:10.981Z",
    "hash": "0845f8c8e1e41d33cbb84e31926958ac"
  },
  "real-change.json": {
    "lastUpdated": "2025-03-29T04:17:10.983Z",
    "hash": "31432a6c23414d7f9362feadc3c01f9f"
  },
  "realizing-the-need-to-prepare.json": {
    "lastUpdated": "2025-03-29T04:17:10.984Z",
    "hash": "749140eb301770534b36d71eabac144f"
  },
  "relationship-god-unknown.json": {
    "lastUpdated": "2025-03-29T04:17:10.985Z",
    "hash": "85b275005d6e495c80f0059e2a5e1391"
  },
  "relationships-and-sexuality.json": {
    "lastUpdated": "2025-03-29T04:17:10.986Z",
    "hash": "a4f45dfbf9fa3a6640d969952b1112f3"
  },
  "relationships-and-the-great-waves.json": {
    "lastUpdated": "2025-03-29T04:17:10.987Z",
    "hash": "12d712c29c9af01ee712e3b5cffc7ca9"
  },
  "relationships-of-destiny.json": {
    "lastUpdated": "2025-03-29T04:17:10.989Z",
    "hash": "ea33c5b20b5766dc4eeb538ff0f7b087"
  },
  "religion-and-politics.json": {
    "lastUpdated": "2025-03-29T04:17:10.990Z",
    "hash": "eb20608f271f1c1427980311988e98a8"
  },
  "religion-as-education.json": {
    "lastUpdated": "2025-03-29T04:17:10.991Z",
    "hash": "92effd91be2e9c21dc05466a7c73e1a9"
  },
  "religion-as-mystery.json": {
    "lastUpdated": "2025-03-29T04:17:10.993Z",
    "hash": "8205b036b1e196d114f31a5eb8db1492"
  },
  "religion-universe.json": {
    "lastUpdated": "2025-03-29T04:17:10.994Z",
    "hash": "effe38cbe0b6d92a69e8b09426c591dc"
  },
  "religious-fundamentalism.json": {
    "lastUpdated": "2025-03-29T04:17:10.995Z",
    "hash": "fe487edb9a25394e8b60009327fec45d"
  },
  "religious-violence.json": {
    "lastUpdated": "2025-03-29T04:17:10.997Z",
    "hash": "ac8a350dba374586b7077fc48e73e464"
  },
  "remembrance-eternal-life.json": {
    "lastUpdated": "2025-03-29T04:17:10.998Z",
    "hash": "e13f01fd7580aadabaaba9af88fe982d"
  },
  "resilience.json": {
    "lastUpdated": "2025-03-29T04:17:10.999Z",
    "hash": "50da8d467a9c0cc209ce04594fa1f308"
  },
  "resolve-conflict-world.json": {
    "lastUpdated": "2025-03-29T04:17:11.000Z",
    "hash": "de15a39acbd3c95217a790dc93726d8f"
  },
  "responses-definition-intelligence.json": {
    "lastUpdated": "2025-03-29T04:17:11.001Z",
    "hash": "7a13f32b8f8ec8112c83e93b82bcf04e"
  },
  "restoring-the-world.json": {
    "lastUpdated": "2025-03-29T04:17:11.002Z",
    "hash": "ac4f2b68208755d46c4d365fed6d91ea"
  },
  "seal-of-the-prophets.json": {
    "lastUpdated": "2025-03-29T04:17:11.003Z",
    "hash": "d88432c4eb69511c05f31c9a112355e4"
  },
  "seeing-knowing-and-taking-action.json": {
    "lastUpdated": "2025-03-29T04:17:11.004Z",
    "hash": "a4621809086ddd1ac0dee20c1ff7e818"
  },
  "seeing-what-is-coming.json": {
    "lastUpdated": "2025-03-29T04:17:11.006Z",
    "hash": "7df809b80fc272c8a478eb2d03988884"
  },
  "self-confidence.json": {
    "lastUpdated": "2025-03-29T04:17:11.007Z",
    "hash": "a9d8b4b050d7dff2b3e9b40d8047a4c3"
  },
  "self-expression-the-mental-environment.json": {
    "lastUpdated": "2025-03-29T04:17:11.008Z",
    "hash": "1a71eae7e44130720ab0133c1de6d3f3"
  },
  "self-reliance.json": {
    "lastUpdated": "2025-03-29T04:17:11.009Z",
    "hash": "78f36aace1e4482929980180d246c690"
  },
  "serve-others.json": {
    "lastUpdated": "2025-03-29T04:17:11.011Z",
    "hash": "d7586e99a1d9a8f562e463037a9dea9f"
  },
  "service-in-the-world.json": {
    "lastUpdated": "2025-03-29T04:17:11.012Z",
    "hash": "54442785decfdac6f8b07153473b13d2"
  },
  "sexuality-power-purpose.json": {
    "lastUpdated": "2025-03-29T04:17:11.013Z",
    "hash": "8770386e934ef0cfd17b09d1706fe921"
  },
  "sharing-the-way-of-knowledge-with-others.json": {
    "lastUpdated": "2025-03-29T04:17:11.015Z",
    "hash": "a0aa90ca7474c62325e22687de333aef"
  },
  "signs-from-the-world.json": {
    "lastUpdated": "2025-03-29T04:17:11.016Z",
    "hash": "d5542174c046140a91671ebfe5e2ca81"
  },
  "simplicity.json": {
    "lastUpdated": "2025-03-29T04:17:11.017Z",
    "hash": "a856113bf14a066d83d0f2eeb69760fc"
  },
  "solving-problems.json": {
    "lastUpdated": "2025-03-29T04:17:11.018Z",
    "hash": "90ba1e3566fefb8cee3b314571c04f8c"
  },
  "souls-journey-through-life.json": {
    "lastUpdated": "2025-03-29T04:17:11.019Z",
    "hash": "3e39af9ad64c950984f643774789454d"
  },
  "space-travel.json": {
    "lastUpdated": "2025-03-29T04:17:11.020Z",
    "hash": "ea648631e7e5ab0a5e96101cad0b0320"
  },
  "spiritual-community-true-community.json": {
    "lastUpdated": "2025-03-29T04:17:11.022Z",
    "hash": "2c04fa8624dcd792204d12fb4077d95f"
  },
  "spiritual-development-practices.json": {
    "lastUpdated": "2025-03-29T04:17:11.023Z",
    "hash": "45e8f2bb3b4714d0cba63dd0c50745ad"
  },
  "spiritual-families.json": {
    "lastUpdated": "2025-03-29T04:17:11.025Z",
    "hash": "582304921eb1b7ebda5bf52b7ef36361"
  },
  "spiritual-family-2.json": {
    "lastUpdated": "2025-03-29T04:17:11.026Z",
    "hash": "120cf219d9f2ac7fc3e44e47a2034eb4"
  },
  "spiritual-family.json": {
    "lastUpdated": "2025-03-29T04:17:11.028Z",
    "hash": "b1118bcadc8dbb8e29316419b5359dd6"
  },
  "spiritual-practice-find-purpose.json": {
    "lastUpdated": "2025-03-29T04:17:11.029Z",
    "hash": "91af3cc4f670df56a9c71025d2dfebc6"
  },
  "spiritual-retreat.json": {
    "lastUpdated": "2025-03-29T04:17:11.030Z",
    "hash": "d31a9498ec6150720df24ba9fe3654b9"
  },
  "spiritual-revolution.json": {
    "lastUpdated": "2025-03-29T04:17:11.032Z",
    "hash": "5e1aea255f2f11c15e27f5907f3029b8"
  },
  "spiritual-truths.json": {
    "lastUpdated": "2025-03-29T04:17:11.033Z",
    "hash": "be3cf912e540c730ad5bd087eea95ad1"
  },
  "stability-security.json": {
    "lastUpdated": "2025-03-29T04:17:11.034Z",
    "hash": "7d6780eb96af105f2acc50dccad8885d"
  },
  "stages-development-relationship.json": {
    "lastUpdated": "2025-03-29T04:17:11.035Z",
    "hash": "7c38b89efe56af4057c821c09eb593f2"
  },
  "standing-precipice-world-decline.json": {
    "lastUpdated": "2025-03-29T04:17:11.036Z",
    "hash": "f71435790dd9799b2340fbd075ad90e3"
  },
  "steps-knowledge-chapter.json": {
    "lastUpdated": "2025-03-29T04:17:11.037Z",
    "hash": "83b1d94225cc280f246edfe3f9b08258"
  },
  "steps-knowledge-continuation-training-chapter.json": {
    "lastUpdated": "2025-03-29T04:17:11.038Z",
    "hash": "0d3272a826d184a42975d92cb669d58f"
  },
  "stillness.json": {
    "lastUpdated": "2025-03-29T04:17:11.039Z",
    "hash": "7b29b0419d4a28a2350cbf96b3e1c867"
  },
  "suffering.json": {
    "lastUpdated": "2025-03-29T04:17:11.041Z",
    "hash": "af57680710722661f472beb85527f38c"
  },
  "sufficient-health.json": {
    "lastUpdated": "2025-03-29T04:17:11.042Z",
    "hash": "c96747af2d806a41233d13b0a11516fc"
  },
  "supporting-gods-new-revelation.json": {
    "lastUpdated": "2025-03-29T04:17:11.044Z",
    "hash": "0aa0b71d37f732a813674f667b7d6fc3"
  },
  "taking-the-steps-to-knowledge.json": {
    "lastUpdated": "2025-03-29T04:17:11.045Z",
    "hash": "6b1e0c9ececdebe0e38e9b5ed16f9e66"
  },
  "the-age-of-women.json": {
    "lastUpdated": "2025-03-29T04:17:11.046Z",
    "hash": "6c2ca219dc21bb35ff32fc0297dcfa4f"
  },
  "the-art-of-seeing.json": {
    "lastUpdated": "2025-03-29T04:17:11.047Z",
    "hash": "fbc19de3145f8df1c82a699fb50b934c"
  },
  "the-assembly.json": {
    "lastUpdated": "2025-03-29T04:17:11.048Z",
    "hash": "9280612063d49aa9cccc95f4414151ac"
  },
  "the-awakening.json": {
    "lastUpdated": "2025-03-29T04:17:11.049Z",
    "hash": "80ca3f327b0ed7110d89742f1d9167a9"
  },
  "the-blessing.json": {
    "lastUpdated": "2025-03-29T04:17:11.051Z",
    "hash": "5d0c725ea66f1295cb26ce9013268550"
  },
  "the-calling.json": {
    "lastUpdated": "2025-03-29T04:17:11.051Z",
    "hash": "1938afea78858dbea641272d1940e472"
  },
  "the-condition-of-the-world.json": {
    "lastUpdated": "2025-03-29T04:17:11.052Z",
    "hash": "66c396c181bb825be97756a566986086"
  },
  "the-confirmation.json": {
    "lastUpdated": "2025-03-29T04:17:11.053Z",
    "hash": "e35c94e2f21f89c27f063432d3b17ef9"
  },
  "the-consequence-of-revelation.json": {
    "lastUpdated": "2025-03-29T04:17:11.055Z",
    "hash": "522a05d5846c279185307c5f6d4035b7"
  },
  "the-crisis.json": {
    "lastUpdated": "2025-03-29T04:17:11.057Z",
    "hash": "80e18da9787005e6c1c9084777c60d39"
  },
  "the-danger-of-isolation.json": {
    "lastUpdated": "2025-03-29T04:17:11.058Z",
    "hash": "8fed8315f169481d471b83980e6165d4"
  },
  "the-deep-evaluation.json": {
    "lastUpdated": "2025-03-29T04:17:11.059Z",
    "hash": "fcec9126cdaaaace11c0f2f888754a99"
  },
  "the-determination.json": {
    "lastUpdated": "2025-03-29T04:17:11.061Z",
    "hash": "776b875010d8c42a58ac05f95773d34f"
  },
  "the-effects-of-the-pacification-program.json": {
    "lastUpdated": "2025-03-29T04:17:11.062Z",
    "hash": "0b0acbdbb9f2793c27370a1b92583390"
  },
  "the-engagement.json": {
    "lastUpdated": "2025-03-29T04:17:11.063Z",
    "hash": "724b9a39ed4e00d90c426e8a2d13db3c"
  },
  "the-engine-of-war.json": {
    "lastUpdated": "2025-03-29T04:17:11.064Z",
    "hash": "b6cc99b899ddcca4a7bcabc9031aee88"
  },
  "the-fate-of-nations.json": {
    "lastUpdated": "2025-03-29T04:17:11.065Z",
    "hash": "373022b3c19cc184ca7dbb0b33238cf2"
  },
  "the-four-pillars-of-life.json": {
    "lastUpdated": "2025-03-29T04:17:11.067Z",
    "hash": "eed74e6e866c74be0fac4534cc2525b4"
  },
  "the-freedom-to-move-with-knowledge.json": {
    "lastUpdated": "2025-03-29T04:17:11.068Z",
    "hash": "84a9f451eaea74fd10914a0cedcc46d9"
  },
  "the-gift-of-a-new-life.json": {
    "lastUpdated": "2025-03-29T04:17:11.069Z",
    "hash": "b5e3cb21af164dbe679ed4141867beb5"
  },
  "the-global-emergency.json": {
    "lastUpdated": "2025-03-29T04:17:11.070Z",
    "hash": "17b46c08c723f16da2ebaa49b4424444"
  },
  "the-goal-and-purpose-of-the-revelation.json": {
    "lastUpdated": "2025-03-29T04:17:11.073Z",
    "hash": "32f7bb6f0a5b02a42c08c5bc3253e21d"
  },
  "the-great-faith.json": {
    "lastUpdated": "2025-03-29T04:17:11.075Z",
    "hash": "b8ef697ce6491713152771fe9f79a9b0"
  },
  "the-great-love.json": {
    "lastUpdated": "2025-03-29T04:17:11.076Z",
    "hash": "5f8217ef9bb41121cbb2678d8ee688ba"
  },
  "the-great-threshold.json": {
    "lastUpdated": "2025-03-29T04:17:11.077Z",
    "hash": "eb7fa7673d29c90ddc3294996c820698"
  },
  "the-great-turning-point-for-humanity.json": {
    "lastUpdated": "2025-03-29T04:17:11.078Z",
    "hash": "efa92d9b9d0586c0e677fef7a5ab5b6f"
  },
  "the-great-warning.json": {
    "lastUpdated": "2025-03-29T04:17:11.080Z",
    "hash": "e92126e25498a777fccfbbf010f6b779"
  },
  "the-great-waves-and-the-hidden-reality-of-contact.json": {
    "lastUpdated": "2025-03-29T04:17:11.081Z",
    "hash": "ec5e047c47da640b2bb9c82d1e01b77c"
  },
  "the-great-waves-and-your-life.json": {
    "lastUpdated": "2025-03-29T04:17:11.082Z",
    "hash": "8072dee259c156c2561eebdb6aa9b23e"
  },
  "the-great-waves-of-change-vol5.json": {
    "lastUpdated": "2025-03-29T04:17:11.083Z",
    "hash": "f11e517482dc4ab6141e35ec4b358424"
  },
  "the-great-waves-of-change.json": {
    "lastUpdated": "2025-03-29T04:17:11.084Z",
    "hash": "6750d754df89fc3f0b914f5e305dc70c"
  },
  "the-great-waves-prophecy.json": {
    "lastUpdated": "2025-03-29T04:17:11.085Z",
    "hash": "a57d44c139902096fcda083779f3b690"
  },
  "the-greater-community-chapter-3.json": {
    "lastUpdated": "2025-03-29T04:17:11.086Z",
    "hash": "c87bf087a640ff714d3c512683ae36c2"
  },
  "the-greater-intelligence.json": {
    "lastUpdated": "2025-03-29T04:17:11.087Z",
    "hash": "bc0612d8ea8952ab5255cf03b6a6528d"
  },
  "the-greater-mind-of-knowledge.json": {
    "lastUpdated": "2025-03-29T04:17:11.088Z",
    "hash": "458ecc6f677a245462d6f319ca080083"
  },
  "the-greater-religion.json": {
    "lastUpdated": "2025-03-29T04:17:11.090Z",
    "hash": "678abf8d9ecafa30bd62af71b6e2614f"
  },
  "the-guardians.json": {
    "lastUpdated": "2025-03-29T04:17:11.092Z",
    "hash": "b11f2c89753df99fedc4df346e59e3e9"
  },
  "the-heart-of-god.json": {
    "lastUpdated": "2025-03-29T04:17:11.094Z",
    "hash": "4a244780c0923ecc09690245e2f01817"
  },
  "the-holy-days.json": {
    "lastUpdated": "2025-03-29T04:17:11.095Z",
    "hash": "e6f6a380b2af010101837c168c87f30f"
  },
  "the-illumination.json": {
    "lastUpdated": "2025-03-29T04:17:11.096Z",
    "hash": "48b81c3e747ca33663552f08529e8254"
  },
  "the-importance-of-the-individual.json": {
    "lastUpdated": "2025-03-29T04:17:11.097Z",
    "hash": "76c68ea96408ff174b4a99c8df810520"
  },
  "the-initiation.json": {
    "lastUpdated": "2025-03-29T04:17:11.098Z",
    "hash": "8e3305ecf079366cf04ab7b813ba5684"
  },
  "the-inner-voice.json": {
    "lastUpdated": "2025-03-29T04:17:11.099Z",
    "hash": "a4ca4bee4d6e97f4a13ca7cb7d23d8b4"
  },
  "the-journey-of-the-messenger.json": {
    "lastUpdated": "2025-03-29T04:17:11.100Z",
    "hash": "d65a38da2897e1d2fa1f2677635e79ce"
  },
  "the-journey-to-a-new-life.json": {
    "lastUpdated": "2025-03-29T04:17:11.101Z",
    "hash": "520e4ade5b79a8a7002a95f5f3596d0c"
  },
  "the-meaning-of-christmas.json": {
    "lastUpdated": "2025-03-29T04:17:11.102Z",
    "hash": "e59d89c190cec76e373a5a12e5ab1335"
  },
  "the-message-and-the-messenger.json": {
    "lastUpdated": "2025-03-29T04:17:11.103Z",
    "hash": "6a1f829811133c9a1814ee2ab80f69eb"
  },
  "the-messengers-calling.json": {
    "lastUpdated": "2025-03-29T04:17:11.105Z",
    "hash": "8131c6c3dc6cb515391ffdeb9dd9d9a0"
  },
  "the-miracle.json": {
    "lastUpdated": "2025-03-29T04:17:11.106Z",
    "hash": "eebe6b8510351131984797985b3bf629"
  },
  "the-mysterious-path-of-revelation.json": {
    "lastUpdated": "2025-03-29T04:17:11.108Z",
    "hash": "4ba2bf9232dd4e983fe70bdb4a420464"
  },
  "the-new-god-experience-vol2.json": {
    "lastUpdated": "2025-03-29T04:17:11.109Z",
    "hash": "76964d1b921bf54a0ea4539c37bfaaec"
  },
  "the-new-god-experience.json": {
    "lastUpdated": "2025-03-29T04:17:11.110Z",
    "hash": "ad0e4e6fee021009f9f0e387358a55d1"
  },
  "the-new-message-for-the-impoverished-and-oppressed.json": {
    "lastUpdated": "2025-03-29T04:17:11.112Z",
    "hash": "9efc983f9c294d20f9aa675079b5da64"
  },
  "the-new-messenger-chapter-1.json": {
    "lastUpdated": "2025-03-29T04:17:11.113Z",
    "hash": "6e028da6a4d8b5991bbfb6d6573d396c"
  },
  "the-new-way-forward-for-humanity.json": {
    "lastUpdated": "2025-03-29T04:17:11.114Z",
    "hash": "d4acbfc27fda9e31e77e1de51aa72cc4"
  },
  "the-night-meditation.json": {
    "lastUpdated": "2025-03-29T04:17:11.115Z",
    "hash": "7972b2e24bb6f7e533fdeb0dec4f3d77"
  },
  "the-one-god-chapter-2.json": {
    "lastUpdated": "2025-03-29T04:17:11.116Z",
    "hash": "26047861d119650cb9147f765927ddbc"
  },
  "the-one-god-chapter-3.json": {
    "lastUpdated": "2025-03-29T04:17:11.117Z",
    "hash": "8858ca9451a8cca978f31c5c9010e702"
  },
  "the-one-god-english-ebook.json": {
    "lastUpdated": "2025-03-29T04:17:11.119Z",
    "hash": "587b67526b9e0e0eac65ad45b6639240"
  },
  "the-one-god-english-print-book.json": {
    "lastUpdated": "2025-03-29T04:17:11.120Z",
    "hash": "d711c28522412db7fcc5867456f7ecc1"
  },
  "the-origin.json": {
    "lastUpdated": "2025-03-29T04:17:11.121Z",
    "hash": "c8f5c65ea6b7976c3ba76df707f2d5c2"
  },
  "the-pilgrimage.json": {
    "lastUpdated": "2025-03-29T04:17:11.123Z",
    "hash": "82593a2cf076f406b1cc27d49aa38e5f"
  },
  "the-power-of-seeing-and-knowing.json": {
    "lastUpdated": "2025-03-29T04:17:11.124Z",
    "hash": "df2bfd79384a9db00daf21fbd79ec179"
  },
  "the-problem-of-human-denial.json": {
    "lastUpdated": "2025-03-29T04:17:11.126Z",
    "hash": "3deb70b6b3e0ebd200741dfc78a4eb48"
  },
  "the-proclamation.json": {
    "lastUpdated": "2025-03-29T04:17:11.127Z",
    "hash": "79462f4676ffa440646df8226a242d26"
  },
  "the-prophet.json": {
    "lastUpdated": "2025-03-29T04:17:11.129Z",
    "hash": "d1e5427414318be176ff5ca61fba0ddb"
  },
  "the-pure-religion.json": {
    "lastUpdated": "2025-03-29T04:17:11.129Z",
    "hash": "7d25945f5ddffac602ec27e30a6a52d6"
  },
  "the-purpose-of-religion.json": {
    "lastUpdated": "2025-03-29T04:17:11.130Z",
    "hash": "5703dc404541f518e0fac3611d8f8840"
  },
  "the-race-to-save-human-civilization.json": {
    "lastUpdated": "2025-03-29T04:17:11.132Z",
    "hash": "023fb7c03d37ee90e56b20bf6b0c18ff"
  },
  "the-rays-of-initiation.json": {
    "lastUpdated": "2025-03-29T04:17:11.133Z",
    "hash": "55089b49dbab9abe161082b15b17e998"
  },
  "the-recitation.json": {
    "lastUpdated": "2025-03-29T04:17:11.134Z",
    "hash": "48af397075b6964138be8dd4e1bc4224"
  },
  "the-reconciliation.json": {
    "lastUpdated": "2025-03-29T04:17:11.135Z",
    "hash": "5fb314e4884af0be1b9078f01837eecd"
  },
  "the-redeemer.json": {
    "lastUpdated": "2025-03-29T04:17:11.137Z",
    "hash": "e506230885ad3b13705fa2c60e097140"
  },
  "the-reformation.json": {
    "lastUpdated": "2025-03-29T04:17:11.138Z",
    "hash": "9fbfcd42e81e27edf524bb4907ccdb8f"
  },
  "the-requirements-of-the-messenger.json": {
    "lastUpdated": "2025-03-29T04:17:11.139Z",
    "hash": "256aeab6b3d0292b693dd3bd1118b108"
  },
  "the-sacred-life.json": {
    "lastUpdated": "2025-03-29T04:17:11.140Z",
    "hash": "ad51b8cc30ee773b4299aad2ba2a7c2e"
  },
  "the-sacred-rendezvous.json": {
    "lastUpdated": "2025-03-29T04:17:11.142Z",
    "hash": "5a43a060f9874902d08c233387cd51de"
  },
  "the-sacred.json": {
    "lastUpdated": "2025-03-29T04:17:11.143Z",
    "hash": "cd345a105a1db6e716ae1d3e1bd0b460"
  },
  "the-separation.json": {
    "lastUpdated": "2025-03-29T04:17:11.144Z",
    "hash": "f141d70cd8abb59e0872281679765850"
  },
  "the-ship.json": {
    "lastUpdated": "2025-03-29T04:17:11.145Z",
    "hash": "06ab67b5693652ba7caf965606646f62"
  },
  "the-shock-of-the-future.json": {
    "lastUpdated": "2025-03-29T04:17:11.146Z",
    "hash": "cf305d8b75b1cf7beb3690b06bf8222c"
  },
  "the-soul.json": {
    "lastUpdated": "2025-03-29T04:17:11.147Z",
    "hash": "e63127be41c52f448ca045a073859c86"
  },
  "the-spiritual-fire.json": {
    "lastUpdated": "2025-03-29T04:17:11.148Z",
    "hash": "4ab08fc70ad6086242ef5165d5beda90"
  },
  "the-still-mind.json": {
    "lastUpdated": "2025-03-29T04:17:11.148Z",
    "hash": "fc0d764e9b568941f4bcfed2395a1439"
  },
  "the-story-of-the-messenger.json": {
    "lastUpdated": "2025-03-29T04:17:11.149Z",
    "hash": "04ee12058361387e1bdba3a2da53cdaf"
  },
  "the-time-of-revelation.json": {
    "lastUpdated": "2025-03-29T04:17:11.151Z",
    "hash": "958cbb43858dcb95c8757444c74608e8"
  },
  "the-turning-point.json": {
    "lastUpdated": "2025-03-29T04:17:11.152Z",
    "hash": "1937f55317c1149142428a42da06385a"
  },
  "the-upheaval.json": {
    "lastUpdated": "2025-03-29T04:17:11.153Z",
    "hash": "62fe582f919cbd2eca9971ef963d3865"
  },
  "the-veil-of-the-messenger.json": {
    "lastUpdated": "2025-03-29T04:17:11.154Z",
    "hash": "96596005f89411bdec521e84a2afcc5e"
  },
  "the-voice-of-the-revelation.json": {
    "lastUpdated": "2025-03-29T04:17:11.155Z",
    "hash": "a24ca5959f9a3b9281e38a375f16558a"
  },
  "the-will-of-heaven.json": {
    "lastUpdated": "2025-03-29T04:17:11.157Z",
    "hash": "3a72666570237e0b6641cce049d6c896"
  },
  "the-world-must-receive-gods-new-message.json": {
    "lastUpdated": "2025-03-29T04:17:11.158Z",
    "hash": "3361a3ae9f113c429d7d8b41c4497f1b"
  },
  "the-world-must-receive.json": {
    "lastUpdated": "2025-03-29T04:17:11.160Z",
    "hash": "185cbd7f3349219550be36751cfb7c5c"
  },
  "three-stages-development.json": {
    "lastUpdated": "2025-03-29T04:17:11.161Z",
    "hash": "d75faf118e718e22375b6e396c636831"
  },
  "trade-commerce-competition.json": {
    "lastUpdated": "2025-03-29T04:17:11.162Z",
    "hash": "5890fcce342071d81a1291bb11b26779"
  },
  "true-inspiration.json": {
    "lastUpdated": "2025-03-29T04:17:11.163Z",
    "hash": "fc8d8cf32c80e0ca0d9ae35d14e17c7f"
  },
  "true-self-knowledge.json": {
    "lastUpdated": "2025-03-29T04:17:11.164Z",
    "hash": "b755efb8bba05d37cfe395a9fb3fe766"
  },
  "trusting-god.json": {
    "lastUpdated": "2025-03-29T04:17:11.166Z",
    "hash": "98631afcb0995f8ec2d636507dee9526"
  },
  "uncertain-future.json": {
    "lastUpdated": "2025-03-29T04:17:11.167Z",
    "hash": "3402e4ef8c3436cac3c4ae1941ca8617"
  },
  "understanding-forgiveness.json": {
    "lastUpdated": "2025-03-29T04:17:11.168Z",
    "hash": "1ef28a9703d1838671142c286cca2195"
  },
  "understanding-money-wealth-and-power.json": {
    "lastUpdated": "2025-03-29T04:17:11.171Z",
    "hash": "0a46d9cc411f58c78d02602b7856f8f9"
  },
  "understanding-the-intervention.json": {
    "lastUpdated": "2025-03-29T04:17:11.173Z",
    "hash": "95a28548b55a515fae3669163e213543"
  },
  "understanding-the-new-messenger.json": {
    "lastUpdated": "2025-03-29T04:17:11.174Z",
    "hash": "912ba4a0aebf21609e063fbc305bdcee"
  },
  "unseen-forces.json": {
    "lastUpdated": "2025-03-29T04:17:11.174Z",
    "hash": "70971ad78a5c2dc07297be193ae72765"
  },
  "using-power-good.json": {
    "lastUpdated": "2025-03-29T04:17:11.176Z",
    "hash": "cccf525487690e437b32ba474554b0f6"
  },
  "vision-future-world.json": {
    "lastUpdated": "2025-03-29T04:17:11.177Z",
    "hash": "ad90a28490955c1a0e51b412ea4d0c61"
  },
  "walking-with-the-messenger.json": {
    "lastUpdated": "2025-03-29T04:17:11.178Z",
    "hash": "8599f38c4f2379db41982d18202d844e"
  },
  "watchtower-paying-attention-world.json": {
    "lastUpdated": "2025-03-29T04:17:11.179Z",
    "hash": "e6ecf3d5779c7ecbcaf5af15cf0b026a"
  },
  "way-knowledge-beyond-beliefs.json": {
    "lastUpdated": "2025-03-29T04:17:11.181Z",
    "hash": "461e81fe2d172c80fe0bc588b45311f0"
  },
  "what-creates-evil.json": {
    "lastUpdated": "2025-03-29T04:17:11.182Z",
    "hash": "967920a85bc097062960e4f236c71c64"
  },
  "what-does-discretion-mean.json": {
    "lastUpdated": "2025-03-29T04:17:11.182Z",
    "hash": "2297be5d407ae63d5daf827139dc586a"
  },
  "what-god-wills-for-you.json": {
    "lastUpdated": "2025-03-29T04:17:11.183Z",
    "hash": "19f2cd6af6faf5ca22cc99f4d91a046f"
  },
  "what-happens-after-death.json": {
    "lastUpdated": "2025-03-29T04:17:11.185Z",
    "hash": "336073e77ffc0f3a54de01261d9221d4"
  },
  "what-is-creation.json": {
    "lastUpdated": "2025-03-29T04:17:11.186Z",
    "hash": "42508b20dd8bccde235080db9715e803"
  },
  "what-is-discernment.json": {
    "lastUpdated": "2025-03-29T04:17:11.187Z",
    "hash": "057f553c89b679b40885d44228fdaad6"
  },
  "what-is-god.json": {
    "lastUpdated": "2025-03-29T04:17:11.188Z",
    "hash": "6626e79b262a32655e60b58d5763c595"
  },
  "what-is-grace.json": {
    "lastUpdated": "2025-03-29T04:17:11.190Z",
    "hash": "5c8d0eb28c0ba6f2b56201ff4886a6e2"
  },
  "what-is-human-destiny.json": {
    "lastUpdated": "2025-03-29T04:17:11.191Z",
    "hash": "4fb34cf75aabe69b5697f1719a3e3050"
  },
  "what-is-human-purpose.json": {
    "lastUpdated": "2025-03-29T04:17:11.192Z",
    "hash": "41da2710e2aeb27d01e815d351b52e09"
  },
  "what-is-knowledge.json": {
    "lastUpdated": "2025-03-29T04:17:11.193Z",
    "hash": "9f6bf85922b2abba880a967a55ef8f23"
  },
  "what-is-life-force.json": {
    "lastUpdated": "2025-03-29T04:17:11.194Z",
    "hash": "6315378c834431c470313b0df70251e9"
  },
  "what-is-redemption.json": {
    "lastUpdated": "2025-03-29T04:17:11.195Z",
    "hash": "cbf9108a4b1736a2a1f3ee193061dcbf"
  },
  "what-is-religion.json": {
    "lastUpdated": "2025-03-29T04:17:11.196Z",
    "hash": "6058c8c4a13a97020376cb00c87e15b9"
  },
  "what-is-religious-education-and-who-is-it-for.json": {
    "lastUpdated": "2025-03-29T04:17:11.198Z",
    "hash": "19b44b2e20c31b9386b2d000b53713b0"
  },
  "what-is-self-doubt.json": {
    "lastUpdated": "2025-03-29T04:17:11.199Z",
    "hash": "828e707c68c67272cde7c3955d662996"
  },
  "what-is-steps-to-knowledge.json": {
    "lastUpdated": "2025-03-29T04:17:11.200Z",
    "hash": "545e1c2ca6e5497f88a2cca7bb94fccd"
  },
  "what-is-the-evolution-of-religion-in-the-world.json": {
    "lastUpdated": "2025-03-29T04:17:11.201Z",
    "hash": "378af6652614bdf9a90fbde9cf4ff4a5"
  },
  "what-is-the-greater-community-way-of-knowledge.json": {
    "lastUpdated": "2025-03-29T04:17:11.202Z",
    "hash": "42bf2dba48356b1914ab31436aa29d39"
  },
  "what-is-the-greater-community.json": {
    "lastUpdated": "2025-03-29T04:17:11.203Z",
    "hash": "c6e5b965dd251edea20c7c5c00c57f88"
  },
  "what-is-the-world.json": {
    "lastUpdated": "2025-03-29T04:17:11.204Z",
    "hash": "be5c2c7aaf295b18f2b58a3b12763ff0"
  },
  "what-is-your-preparation-for.json": {
    "lastUpdated": "2025-03-29T04:17:11.205Z",
    "hash": "a41e2f5d7b38227981ef033a7acf3dd8"
  },
  "what-must-be-avoided.json": {
    "lastUpdated": "2025-03-29T04:17:11.207Z",
    "hash": "c182170840690ba1e25b4e011ba892db"
  },
  "what-must-be-unlearned.json": {
    "lastUpdated": "2025-03-29T04:17:11.208Z",
    "hash": "776d23b9c34ff5e02c69088bca96c495"
  },
  "what-really-matters.json": {
    "lastUpdated": "2025-03-29T04:17:11.209Z",
    "hash": "59b6d895ea96edb40c1d3cd9499ae410"
  },
  "what-will-change-the-world.json": {
    "lastUpdated": "2025-03-29T04:17:11.210Z",
    "hash": "b8690398d9d9ca2cc54fd132bb7507ee"
  },
  "what-will-save-humanity.json": {
    "lastUpdated": "2025-03-29T04:17:11.211Z",
    "hash": "b238a7271638f9527219869547e518ed"
  },
  "where-can-knowledge-be-found.json": {
    "lastUpdated": "2025-03-29T04:17:11.212Z",
    "hash": "a142fbe6b9ef70b27eef3818b2002adc"
  },
  "where-will-you-place-your-faith.json": {
    "lastUpdated": "2025-03-29T04:17:11.213Z",
    "hash": "fd56df1547f7477375183691fd4eb56f"
  },
  "who-are-the-allies-of-humanity.json": {
    "lastUpdated": "2025-03-29T04:17:11.215Z",
    "hash": "96c4cacf5f521224a089292dfaf3bdf0"
  },
  "who-are-the-unseen-ones.json": {
    "lastUpdated": "2025-03-29T04:17:11.216Z",
    "hash": "d5278b330cffe18dbf097c70d5fd1faf"
  },
  "who-can-you-trust.json": {
    "lastUpdated": "2025-03-29T04:17:11.217Z",
    "hash": "9ebf74442c9536429fe0d5010eb1fd39"
  },
  "who-is-jesus.json": {
    "lastUpdated": "2025-03-29T04:17:11.218Z",
    "hash": "975800abc6408a21c22b8a118bd2d3a6"
  },
  "who-is-wisdom-meant-for.json": {
    "lastUpdated": "2025-03-29T04:17:11.219Z",
    "hash": "81740715c8472d1394f014f10aadccba"
  },
  "who-serves-humanity.json": {
    "lastUpdated": "2025-03-29T04:17:11.220Z",
    "hash": "89cd1dcf0808330722c95fedb0de9a77"
  },
  "whom-will-you-meet.json": {
    "lastUpdated": "2025-03-29T04:17:11.221Z",
    "hash": "8fbbab8b88fe6aa854a4b889c875fb9b"
  },
  "witnessing-the-revelation.json": {
    "lastUpdated": "2025-03-29T04:17:11.222Z",
    "hash": "4bc0335a6dcbef4e8e4970df142e6bd1"
  },
  "work-spiritual-growth.json": {
    "lastUpdated": "2025-03-29T04:17:11.223Z",
    "hash": "3c3748b5b70540c5f78fc54e15db8d4b"
  },
  "working-with-the-mind.json": {
    "lastUpdated": "2025-03-29T04:17:11.225Z",
    "hash": "f31d60e974fe1c1b00efaefbfe89a6d9"
  },
  "world-evolution-global-community.json": {
    "lastUpdated": "2025-03-29T04:17:11.226Z",
    "hash": "a38966279eb7c0bffe8f517978cef7e9"
  },
  "worldwide-community-gods-new-message.json": {
    "lastUpdated": "2025-03-29T04:17:11.227Z",
    "hash": "8862c93b52e522ddb438819f31b613b3"
  },
  "you-are-not-your-mind.json": {
    "lastUpdated": "2025-03-29T04:17:11.229Z",
    "hash": "58e4a0212630b58d69062d8cfd30e0d9"
  },
  "your-most-primary-relationship.json": {
    "lastUpdated": "2025-03-29T04:17:11.230Z",
    "hash": "f0797ec5b33727b0a31e5ab2a72083b8"
  },
  "your-purpose-and-destiny-in-a-changing-world.json": {
    "lastUpdated": "2025-03-29T04:17:11.231Z",
    "hash": "aece8e1f03389c280117c41a691994dc"
  },
  "your-purpose-and-spiritual-calling.json": {
    "lastUpdated": "2025-03-29T04:17:11.232Z",
    "hash": "573061ddcbe195b2bf2356541ff326b6"
  },
  "your-relationship-with-others.json": {
    "lastUpdated": "2025-03-29T04:17:11.233Z",
    "hash": "c81e41f77e2b1669c7eb0f79501ef18e"
  },
  "your-relationship-with-the-messenger.json": {
    "lastUpdated": "2025-03-29T04:17:11.234Z",
    "hash": "b9f972c17ea39962dff9590586addd4d"
  },
  "your-relationship-with-the-world.json": {
    "lastUpdated": "2025-03-29T04:17:11.235Z",
    "hash": "d16c6f7aba5e225638acdb95a5c41273"
  },
  "your-relationship-with-your-spiritual-family.json": {
    "lastUpdated": "2025-03-29T04:17:11.236Z",
    "hash": "e0159bc0478a609e457789a79425a6eb"
  },
  "your-relationship-with-yourself.json": {
    "lastUpdated": "2025-03-29T04:17:11.237Z",
    "hash": "525f417c9f3318dc829d3d9b21ad420c"
  },
  "your-spiritual-family.json": {
    "lastUpdated": "2025-03-29T04:17:11.237Z",
    "hash": "c86e147e516a695bebfc7aad7b2e0b5d"
  },
  "scraped-navigation.json": {
    "lastUpdated": "2025-03-30T01:58:40.496Z",
    "hash": "58c66d729edf25cfaf3dc6e713d992b2"
  }
}